MANIFEST.in
README.rst
setup.cfg
setup.py
hit_csys/DVM-Parameter_v2.10.0-HIT.csv
hit_csys/__init__.py
hit_csys/beamoptikdll.py
hit_csys/dvm_parameters.py
hit_csys/gui_qt.py
hit_csys/gui_win32.py
hit_csys/gui_wx.py
hit_csys/offsets.py
hit_csys/plugin.py
hit_csys/stub.py
hit_csys/util.py
hit_csys.egg-info/PKG-INFO
hit_csys.egg-info/SOURCES.txt
hit_csys.egg-info/dependency_links.txt
hit_csys.egg-info/entry_points.txt
hit_csys.egg-info/requires.txt
hit_csys.egg-info/top_level.txt