Metadata-Version: 1.1
Name: hit-csys
Version: 18.10.0
Summary: Online control for the HIT accelerator facility.
Home-page: https://github.com/hibtc/hit-csys
Author: Thomas Gläßle
Author-email: t_glaessle@gmx.de
License: UNKNOWN
Platform: UNKNOWN
Classifier: Development Status :: 3 - Alpha
Classifier: Intended Audience :: Developers
Classifier: Intended Audience :: Healthcare Industry
Classifier: Intended Audience :: Science/Research
Classifier: Operating System :: OS Independent
Classifier: Programming Language :: Python
Classifier: Topic :: Scientific/Engineering :: Medical Science Apps.
Classifier: Topic :: Scientific/Engineering :: Physics
